{
  "slug": "goldi_hub_instant_1784124839",
  "name": "Goldi_Hub_instant_1784124839",
  "server_name": "Goldi_Hub",
  "tournament_name": "instant_1784124839",
  "tournament_type": "single elimination",
  "status": "ongoing",
  "current_round": 1,
  "updated_at": "2026-07-15T14:19:55.559797+00:00",
  "participants": [
    {
      "id": 719,
      "tournament_id": 63,
      "seed": 1,
      "display_name": "Art",
      "external_id": "886500802540216321",
      "losses": 0,
      "eliminated": 0,
      "eliminated_round": null,
      "created_at": "2026-07-15T14:13:59.779793+00:00"
    },
    {
      "id": 720,
      "tournament_id": 63,
      "seed": 2,
      "display_name": "Shre\u03b3\u03b1sh",
      "external_id": "1339340207454949426",
      "losses": 0,
      "eliminated": 0,
      "eliminated_round": null,
      "created_at": "2026-07-15T14:13:59.779793+00:00"
    },
    {
      "id": 721,
      "tournament_id": 63,
      "seed": 3,
      "display_name": "Kattar brajil fan\ud83d\udc94\ud83d\udc94\ud83d\udc94",
      "external_id": "1352826691583475712",
      "losses": 0,
      "eliminated": 0,
      "eliminated_round": null,
      "created_at": "2026-07-15T14:13:59.779793+00:00"
    },
    {
      "id": 722,
      "tournament_id": 63,
      "seed": 4,
      "display_name": "SoL",
      "external_id": "1376286830558974166",
      "losses": 0,
      "eliminated": 0,
      "eliminated_round": null,
      "created_at": "2026-07-15T14:13:59.779793+00:00"
    },
    {
      "id": 723,
      "tournament_id": 63,
      "seed": 5,
      "display_name": "Belisarius",
      "external_id": "841638101213511741",
      "losses": 0,
      "eliminated": 0,
      "eliminated_round": null,
      "created_at": "2026-07-15T14:13:59.779793+00:00"
    },
    {
      "id": 724,
      "tournament_id": 63,
      "seed": 6,
      "display_name": "Future tesla",
      "external_id": "981969143358160946",
      "losses": 0,
      "eliminated": 0,
      "eliminated_round": null,
      "created_at": "2026-07-15T14:13:59.779793+00:00"
    },
    {
      "id": 725,
      "tournament_id": 63,
      "seed": 7,
      "display_name": "finesse",
      "external_id": "1114417385898778684",
      "losses": 0,
      "eliminated": 0,
      "eliminated_round": null,
      "created_at": "2026-07-15T14:13:59.779793+00:00"
    },
    {
      "id": 726,
      "tournament_id": 63,
      "seed": 8,
      "display_name": "R\u028f\u1d1c\u0262\u1d1c\u1d0a\u026a K\u1d07\u0274\u2713",
      "external_id": "1290358369944600619",
      "losses": 1,
      "eliminated": 1,
      "eliminated_round": 1,
      "created_at": "2026-07-15T14:13:59.779793+00:00"
    }
  ],
  "matches": [
    {
      "id": 848,
      "tournament_id": 63,
      "bracket": "W",
      "round_id": 1,
      "match_order": 1,
      "player1_participant_id": 726,
      "player2_participant_id": 725,
      "winner_participant_id": 725,
      "loser_participant_id": 726,
      "state": "complete",
      "scores_csv": "0-1",
      "player1_prereq_match_id": null,
      "player2_prereq_match_id": null,
      "next_match_win_id": 852,
      "next_match_win_slot": 1,
      "next_match_lose_id": null,
      "next_match_lose_slot": null,
      "created_at": "2026-07-15T14:13:59.780316+00:00",
      "updated_at": "2026-07-15T14:19:55.538613+00:00"
    },
    {
      "id": 849,
      "tournament_id": 63,
      "bracket": "W",
      "round_id": 1,
      "match_order": 2,
      "player1_participant_id": 723,
      "player2_participant_id": 722,
      "winner_participant_id": null,
      "loser_participant_id": null,
      "state": "open",
      "scores_csv": null,
      "player1_prereq_match_id": null,
      "player2_prereq_match_id": null,
      "next_match_win_id": 852,
      "next_match_win_slot": 2,
      "next_match_lose_id": null,
      "next_match_lose_slot": null,
      "created_at": "2026-07-15T14:13:59.780387+00:00",
      "updated_at": "2026-07-15T14:13:59.780418+00:00"
    },
    {
      "id": 850,
      "tournament_id": 63,
      "bracket": "W",
      "round_id": 1,
      "match_order": 3,
      "player1_participant_id": 721,
      "player2_participant_id": 724,
      "winner_participant_id": null,
      "loser_participant_id": null,
      "state": "open",
      "scores_csv": null,
      "player1_prereq_match_id": null,
      "player2_prereq_match_id": null,
      "next_match_win_id": 853,
      "next_match_win_slot": 1,
      "next_match_lose_id": null,
      "next_match_lose_slot": null,
      "created_at": "2026-07-15T14:13:59.780400+00:00",
      "updated_at": "2026-07-15T14:13:59.780450+00:00"
    },
    {
      "id": 851,
      "tournament_id": 63,
      "bracket": "W",
      "round_id": 1,
      "match_order": 4,
      "player1_participant_id": 719,
      "player2_participant_id": 720,
      "winner_participant_id": null,
      "loser_participant_id": null,
      "state": "open",
      "scores_csv": null,
      "player1_prereq_match_id": null,
      "player2_prereq_match_id": null,
      "next_match_win_id": 853,
      "next_match_win_slot": 2,
      "next_match_lose_id": null,
      "next_match_lose_slot": null,
      "created_at": "2026-07-15T14:13:59.780408+00:00",
      "updated_at": "2026-07-15T14:13:59.780450+00:00"
    },
    {
      "id": 852,
      "tournament_id": 63,
      "bracket": "W",
      "round_id": 2,
      "match_order": 1,
      "player1_participant_id": 725,
      "player2_participant_id": null,
      "winner_participant_id": null,
      "loser_participant_id": null,
      "state": "open",
      "scores_csv": null,
      "player1_prereq_match_id": 848,
      "player2_prereq_match_id": 849,
      "next_match_win_id": 854,
      "next_match_win_slot": 1,
      "next_match_lose_id": null,
      "next_match_lose_slot": null,
      "created_at": "2026-07-15T14:13:59.780418+00:00",
      "updated_at": "2026-07-15T14:19:55.538757+00:00"
    },
    {
      "id": 853,
      "tournament_id": 63,
      "bracket": "W",
      "round_id": 2,
      "match_order": 2,
      "player1_participant_id": null,
      "player2_participant_id": null,
      "winner_participant_id": null,
      "loser_participant_id": null,
      "state": "open",
      "scores_csv": null,
      "player1_prereq_match_id": 850,
      "player2_prereq_match_id": 851,
      "next_match_win_id": 854,
      "next_match_win_slot": 2,
      "next_match_lose_id": null,
      "next_match_lose_slot": null,
      "created_at": "2026-07-15T14:13:59.780450+00:00",
      "updated_at": "2026-07-15T14:13:59.780465+00:00"
    },
    {
      "id": 854,
      "tournament_id": 63,
      "bracket": "W",
      "round_id": 3,
      "match_order": 1,
      "player1_participant_id": null,
      "player2_participant_id": null,
      "winner_participant_id": null,
      "loser_participant_id": null,
      "state": "open",
      "scores_csv": null,
      "player1_prereq_match_id": 852,
      "player2_prereq_match_id": 853,
      "next_match_win_id": null,
      "next_match_win_slot": null,
      "next_match_lose_id": null,
      "next_match_lose_slot": null,
      "created_at": "2026-07-15T14:13:59.780465+00:00",
      "updated_at": "2026-07-15T14:13:59.780465+00:00"
    }
  ]
}